newrelic_api/__init__.py
newrelic_api/alert_conditions.py
newrelic_api/alert_conditions_infra.py
newrelic_api/alert_conditions_nrql.py
newrelic_api/alert_policies.py
newrelic_api/application_hosts.py
newrelic_api/application_instances.py
newrelic_api/applications.py
newrelic_api/base.py
newrelic_api/browser_applications.py
newrelic_api/components.py
newrelic_api/dashboards.py
newrelic_api/exceptions.py
newrelic_api/key_transactions.py
newrelic_api/labels.py
newrelic_api/notification_channels.py
newrelic_api/plugins.py
newrelic_api/servers.py
newrelic_api/users.py
newrelic_api/version.py
newrelic_api/tests/__init__.py
newrelic_api/tests/alert_conditions_infra_tests.py
newrelic_api/tests/alert_conditions_nrql_tests.py
newrelic_api/tests/alert_conditions_tests.py
newrelic_api/tests/alert_policies_tests.py
newrelic_api/tests/application_hosts_tests.py
newrelic_api/tests/application_instances_tests.py
newrelic_api/tests/applications_tests.py
newrelic_api/tests/base_tests.py
newrelic_api/tests/browser_applications_tests.py
newrelic_api/tests/components_tests.py
newrelic_api/tests/dashboards_test.py
newrelic_api/tests/key_transactions_tests.py
newrelic_api/tests/labels_tests.py
newrelic_api/tests/notification_channels_tests.py
newrelic_api/tests/plugins_tests.py
newrelic_api/tests/servers_tests.py
newrelic_api/tests/user_tests.py
newrelic_api-1.0.6.dist-info/METADATA
newrelic_api-1.0.6.dist-info/RECORD
newrelic_api-1.0.6.dist-info/WHEEL
newrelic_api-1.0.6.dist-info/top_level.txt
newrelic_api-1.0.6.dist-info/zip-safe
