Metadata-Version: 2.1
Name: newrelic-api
Version: 1.0.6
Summary: A python interface to the New Relic API v2
Home-page: https://github.com/ambitioninc/newrelic-api
Author: Micah Hausler
Author-email: opensource@ambition.com
License: MIT
Platform: UNKNOWN
Classifier: Programming Language :: Python :: 2.7
Classifier: Programming Language :: Python :: 3.3
Classifier: Programming Language :: Python :: 3.4
Classifier: Intended Audience :: Developers
Classifier: License :: OSI Approved :: MIT License
Classifier: Operating System :: OS Independent
Requires-Dist: requests (>=2.0.0)
